test/__init__.py
test/foo.py
testlc/__init__.py
testlc/foo.py
venv/__init__.py
venv/Lib/__init__.py
venv/Lib/site-packages/__init__.py
venv/Scripts/__init__.py
venv/Scripts/easy_install-3.6-script.py
venv/Scripts/easy_install-script.py
venv/Scripts/pip-script.py
venv/Scripts/pip3-script.py
venv/Scripts/pip3.6-script.py
testlc-0.1.dist-info/LICENSE
testlc-0.1.dist-info/METADATA
testlc-0.1.dist-info/WHEEL
testlc-0.1.dist-info/top_level.txt
testlc-0.1.dist-info/RECORD
