Metadata-Version: 2.1
Name: testlc
Version: 0.1
Summary: 在这里写对封装的这个包的简单描 述
Home-page: https://github.com
Author: liuchen
Author-email: 1852752478@qq.com
License: MIT
Download-URL: https://github.com
Keywords: foo
Platform: UNKNOWN
Classifier: Framework :: Django
Classifier: Programming Language :: Python :: 3
Classifier: License :: OSI Approved :: MIT License
Classifier: Operating System :: OS Independent
Requires-Python: >=3.6
License-File: LICENSE
